{"preventUpnDetectSso":false,"silentUpdateTriggered":false,"featureLaunchInfo":{"enableUpnSilentSignin":-1},"previousCrashesInfo":{"crashes":[]},"windowState":{"monitorId":13761487533244482,"x":2926,"y":57,"width":900,"height":1009,"isMaximized":false,"isFullScreen":false},"surfaceHubWindowState":{"monitorId":-1,"x":0,"y":0,"width":400,"height":600,"isMaximized":true,"isFullScreen":false},"restartCommand":{},"upnWindowUserUpn":"11192562@st.neu.edu.vn","userUpn":"","userOid":"03cae4b7-83a9-42f5-9753-3433360ec18a","userTid":"7212a37c-41a9-4402-9f69-ac32c6f76e1a","guestTenantId":"","homeTenantId":"","webAccountId":"","webAccountProviderType":"","launchTime":"1638869971264","desktopZoomLevelV2":3,"guestTenantIds":{},"userAccounts":{},"signedInActiveUser":{},"tidOidMap":{},"isAppFirstRun":false,"upnScreenShowCount":0,"desktopSessionId":"desktop-d977c342-7680-4b8e-95da-2526835e08ba","teamsUrlProtocolsRegistered":false,"lyncUrlProtocolsRegistered":false,"disableWarningOnOpenKeyRegistered":false,"previousElectronVersion":"10.4.7","lastKnownElectronVersion":"10.4.7","signInRestrictionsLicenseType":"Student","roomDeviceSettingsHash":"","machineId":"a294698abc405340eb422b97b3bf3552343d8eec4ddc6fe0430dfeb1632dfca4","deviceInfoId":"f5117ce56eb2137993a2953a71fdc89326fecf884cc41714eb279921326f1692","appPreferenceSettings":{"disableGpu":false,"forceRendererAccessibility":false,"openAtLogin":true,"openAsHidden":false,"runningOnClose":true,"registerAsIMProvider":false},"currentWebLanguage":"en-US","isForeground":false,"previousWebClientVersion":"41/1.0.0.2021112916","isLoggedOut":false,"notificationWindowOnClose":true,"isAppTerminated":false,"restartInfo":null}